{
	"ABI version": 2,
	"version": "2.3",
	"header": ["time", "expire"],
	"functions": [
		{
			"name": "constructor",
			"inputs": [
				{"name":"elector","type":"address"},
				{"name":"vendorName","type":"string"},
				{"name":"profitShare","type":"uint256"},
				{"name":"contactInfo","type":"string"}
			],
			"outputs": [
			]
		},
		{
			"name": "get",
			"inputs": [
			],
			"outputs": [
				{"name":"elector","type":"address"},
				{"name":"vendorName","type":"string"},
				{"name":"profitShare","type":"uint256"},
				{"name":"contactInfo","type":"string"}
			]
		},
		{
			"name": "getElector",
			"inputs": [
			],
			"outputs": [
				{"name":"value0","type":"address"}
			]
		},
		{
			"name": "getVendorName",
			"inputs": [
			],
			"outputs": [
				{"name":"value0","type":"string"}
			]
		},
		{
			"name": "getProfitShare",
			"inputs": [
			],
			"outputs": [
				{"name":"value0","type":"uint256"}
			]
		},
		{
			"name": "getContactInfo",
			"inputs": [
			],
			"outputs": [
				{"name":"value0","type":"string"}
			]
		},
		{
			"name": "setVendorName",
			"inputs": [
				{"name":"value","type":"string"}
			],
			"outputs": [
			]
		},
		{
			"name": "setProfitShare",
			"inputs": [
				{"name":"value","type":"uint256"}
			],
			"outputs": [
			]
		},
		{
			"name": "setContactInfo",
			"inputs": [
				{"name":"value","type":"string"}
			],
			"outputs": [
			]
		},
		{
			"name": "v",
			"inputs": [
			],
			"outputs": [
				{"name":"contractVersion","type":"string"}
			]
		},
		{
			"name": "upgrade",
			"inputs": [
				{"name":"code","type":"cell"}
			],
			"outputs": [
			]
		},
		{
			"name": "elector_",
			"inputs": [
			],
			"outputs": [
				{"name":"elector_","type":"address"}
			]
		},
		{
			"name": "vendorName_",
			"inputs": [
			],
			"outputs": [
				{"name":"vendorName_","type":"string"}
			]
		},
		{
			"name": "profitShare_",
			"inputs": [
			],
			"outputs": [
				{"name":"profitShare_","type":"uint256"}
			]
		},
		{
			"name": "contactInfo_",
			"inputs": [
			],
			"outputs": [
				{"name":"contactInfo_","type":"string"}
			]
		}
	],
	"data": [
	],
	"events": [
	],
	"fields": [
		{"name":"_pubkey","type":"uint256"},
		{"name":"_timestamp","type":"uint64"},
		{"name":"_constructorFlag","type":"bool"},
		{"name":"contractVersion_","type":"string"},
		{"name":"elector_","type":"address"},
		{"name":"vendorName_","type":"string"},
		{"name":"profitShare_","type":"uint256"},
		{"name":"contactInfo_","type":"string"}
	]
}
